.gitignore
CHANGES.rst
README.rst
bootstrap.py
buildout.cfg
setup.cfg
setup.py
test.ini
examples/pyramid.msdeploy/MANIFEST.in
examples/pyramid.msdeploy/Manifest.xml.in
examples/pyramid.msdeploy/Parameters.xml
examples/pyramid.msdeploy/iis_install.stamp.in
examples/pyramid.msdeploy/setup.cfg
examples/pyramid.msdeploy/setup.py
examples/pyramid.msdeploy/web.config.in
examples/sample.msdeploy/MANIFEST.in
examples/sample.msdeploy/Manifest.xml.in
examples/sample.msdeploy/Parameters.xml
examples/sample.msdeploy/iis_fcgi.ini
examples/sample.msdeploy/iis_install.stamp.in
examples/sample.msdeploy/setup.cfg
examples/sample.msdeploy/setup.py
examples/sample.msdeploy/web.config.in
iiswsgi/WebPIList.pt
iiswsgi/__init__.py
iiswsgi/bdist_msdeploy.py
iiswsgi/bdist_webpi.py
iiswsgi/build_msdeploy.py
iiswsgi/clean_webpi.py
iiswsgi/fcgi.py
iiswsgi/filesocket.py
iiswsgi/filesocket.rst
iiswsgi/install_msdeploy.py
iiswsgi/options.py
iiswsgi/server.py
iiswsgi/test_msdeploy.py
iiswsgi/tests.py
iiswsgi.egg-info/PKG-INFO
iiswsgi.egg-info/SOURCES.txt
iiswsgi.egg-info/dependency_links.txt
iiswsgi.egg-info/entry_points.txt
iiswsgi.egg-info/requires.txt
iiswsgi.egg-info/top_level.txt