Metadata-Version: 1.1
Name: iiswsgi
Version: 0.3
Summary: Serve WSGI apps using IIS's modified FastCGI support.
Home-page: http://github.com/rpatterson/iiswsgi
Author: Ross Patterson
Author-email: me@rpatterson.net
License: GPL
Keywords: fcgi iis windows
Platform: UNKNOWN
Classifier: Programming Language :: Python
Classifier: Topic :: Software Development :: Libraries :: Python Modules
